lucy_assist/__init__.py
lucy_assist/admin.py
lucy_assist/apps.py
lucy_assist/conf.py
lucy_assist/constantes.py
lucy_assist/context_processors.py
lucy_assist/signals.py
lucy_assist/urls.py
lucy_assist/migrations/0001_initial.py
lucy_assist/migrations/0002_configurationlucyassist_prompt_complementaire.py
lucy_assist/migrations/0003_configurationlucyassist_crud_views_mapping.py
lucy_assist/migrations/__init__.py
lucy_assist/models/__init__.py
lucy_assist/models/base.py
lucy_assist/models/configuration.py
lucy_assist/models/conversation.py
lucy_assist/models/message.py
lucy_assist/models/project_context_cache.py
lucy_assist/services/__init__.py
lucy_assist/services/bug_notification_service.py
lucy_assist/services/claude_service.py
lucy_assist/services/context_service.py
lucy_assist/services/crud_service.py
lucy_assist/services/gitlab_service.py
lucy_assist/services/project_context_service.py
lucy_assist/services/tool_executor_service.py
lucy_assist/services/tools_definition.py
lucy_assist/services/view_discovery_service.py
lucy_assist/static/lucy_assist/css/lucy-assist.css
lucy_assist/static/lucy_assist/image/icon-lucy.png
lucy_assist/static/lucy_assist/js/lucy-assist.js
lucy_assist/templates/lucy_assist/chatbot_sidebar.html
lucy_assist/templates/lucy_assist/partials/documentation_content.html
lucy_assist/tests/__init__.py
lucy_assist/tests/test_lucy_assist.py
lucy_assist/tests/factories/__init__.py
lucy_assist/tests/factories/lucy_assist_factories.py
lucy_assist/utils/__init__.py
lucy_assist/utils/log_utils.py
lucy_assist/utils/message_utils.py
lucy_assist/utils/token_utils.py
lucy_assist/views/__init__.py
lucy_assist/views/api_views.py
django_lucy_assist-1.1.1.dist-info/METADATA
django_lucy_assist-1.1.1.dist-info/WHEEL
django_lucy_assist-1.1.1.dist-info/top_level.txt
django_lucy_assist-1.1.1.dist-info/RECORD
