Metadata-Version: 2.4
Name: django-lucy-assist
Version: 1.1.1
Summary: Assistant IA intelligent Revolucy pour outil métier
Author-email: Revolucy <hello@revolucy.fr>
Maintainer-email: Maxence <hello@revolucy.fr>
License: MIT
Project-URL: Homepage, https://github.com/revolucy/django-lucy-assist
Project-URL: Documentation, https://github.com/revolucy/django-lucy-assist#readme
Project-URL: Repository, https://github.com/revolucy/django-lucy-assist.git
Project-URL: Issues, https://github.com/revolucy/django-lucy-assist/issues
Keywords: django,chatbot,ai,claude,anthropic,assistant,crm
Classifier: Development Status :: 4 - Beta
Classifier: Environment :: Web Environment
Classifier: Framework :: Django
Classifier: Framework :: Django :: 4.2
Classifier: Framework :: Django :: 5.0
Classifier: Framework :: Django :: 5.1
Classifier: Intended Audience :: Developers
Classifier: License :: OSI Approved :: MIT License
Classifier: Operating System :: OS Independent
Classifier: Programming Language :: Python
Classifier: Programming Language :: Python :: 3
Classifier: Programming Language :: Python :: 3.9
Classifier: Programming Language :: Python :: 3.10
Classifier: Programming Language :: Python :: 3.11
Classifier: Programming Language :: Python :: 3.12
Classifier: Topic :: Internet :: WWW/HTTP
Classifier: Topic :: Scientific/Engineering :: Artificial Intelligence
Requires-Python: >=3.9
Requires-Dist: Django>=4.0
Requires-Dist: anthropic>=0.20.0
Requires-Dist: requests>=2.28.0
Provides-Extra: dev
Requires-Dist: pytest>=7.0.0; extra == "dev"
Requires-Dist: pytest-django>=4.5.0; extra == "dev"
Requires-Dist: factory-boy>=3.3.0; extra == "dev"
Requires-Dist: black>=23.0.0; extra == "dev"
Requires-Dist: isort>=5.12.0; extra == "dev"
Requires-Dist: flake8>=6.0.0; extra == "dev"
Provides-Extra: gitlab
Requires-Dist: python-gitlab>=3.15.0; extra == "gitlab"
